odoo/addons/base_binary_url_import/README.rst
odoo/addons/base_binary_url_import/__init__.py
odoo/addons/base_binary_url_import/__manifest__.py
odoo/addons/base_binary_url_import/data/ir_config_parameter.xml
odoo/addons/base_binary_url_import/i18n/base_binary_url_import.pot
odoo/addons/base_binary_url_import/readme/CONFIGURE.rst
odoo/addons/base_binary_url_import/readme/CONTRIBUTORS.rst
odoo/addons/base_binary_url_import/readme/DESCRIPTION.rst
odoo/addons/base_binary_url_import/readme/ROADMAP.rst
odoo/addons/base_binary_url_import/readme/USAGE.rst
odoo/addons/base_binary_url_import/static/description/icon.png
odoo/addons/base_binary_url_import/static/description/index.html
odoo/addons/base_binary_url_import/wizard/__init__.py
odoo/addons/base_binary_url_import/wizard/base_binary_url_import.py
odoo/addons/base_binary_url_import/wizard/base_binary_url_import_view.xml
odoo13_addon_base_binary_url_import-13.0.1.0.1.dev5.dist-info/METADATA
odoo13_addon_base_binary_url_import-13.0.1.0.1.dev5.dist-info/WHEEL
odoo13_addon_base_binary_url_import-13.0.1.0.1.dev5.dist-info/top_level.txt
odoo13_addon_base_binary_url_import-13.0.1.0.1.dev5.dist-info/RECORD
