Metadata-Version: 2.1
Name: odoo13-addon-base-binary-url-import
Version: 13.0.1.0.1.dev5
Summary: Wizard to import binary files from URL on existing records
Home-page: https://github.com/OCA/server-ux
Author: Camptocamp, Odoo Community Association (OCA)
Author-email: support@odoo-community.org
License: AGPL-3
Platform: UNKNOWN
Classifier: Programming Language :: Python
Classifier: Framework :: Odoo
Classifier: Framework :: Odoo :: 13.0
Classifier: License :: OSI Approved :: GNU Affero General Public License v3
Classifier: Development Status :: 3 - Alpha
Requires-Python: >=3.5
Requires-Dist: odoo13-addon-web-domain-field
Requires-Dist: odoo <13.1dev,>=13.0a
Requires-Dist: rfc6266-parser
